Metadata-Version: 2.1
Name: port-mcp-gateway
Version: 0.0.1
Summary: A gateway for interacting with Port.io through a standardized MCP API
Home-page: https://github.com/port-experimental/port-mcp-gateway
Author: Dan Amzulescu
Author-email: dan.a@port.io
Project-URL: Bug Reports, https://github.com/yourusername/port-mcp-gateway/issues
Project-URL: Source, https://github.com/yourusername/port-mcp-gateway
Keywords: port.io,mcp,api,gateway
Classifier: Development Status :: 4 - Beta
Classifier: Intended Audience :: Developers
Classifier: License :: OSI Approved :: MIT License
Classifier: Programming Language :: Python :: 3
Classifier: Programming Language :: Python :: 3.8
Classifier: Programming Language :: Python :: 3.9
Classifier: Programming Language :: Python :: 3.10
Classifier: Programming Language :: Python :: 3.11
Classifier: Topic :: Software Development :: Libraries :: Python Modules
Requires-Python: >=3.8
